wisent/__init__.py
wisent/cli.py
wisent/comparison/__init__.py
wisent/comparison/detect_bos_features.py
wisent/comparison/fgaa.py
wisent/comparison/lora.py
wisent/comparison/lora_dpo.py
wisent/comparison/main.py
wisent/comparison/ours.py
wisent/comparison/reft.py
wisent/comparison/sae.py
wisent/comparison/utils.py
wisent/core/__init__.py
wisent/core/autonomous_agent.py
wisent/core/benchmark_extractors.py
wisent/core/benchmark_registry.py
wisent/core/bigcode_extractors.py
wisent/core/bigcode_integration.py
wisent/core/branding.py
wisent/core/cli_logger.py
wisent/core/config_manager.py
wisent/core/detection_handling.py
wisent/core/diversity_processors.py
wisent/core/download_full_benchmarks.py
wisent/core/geometry_runner.py
wisent/core/geometry_search_space.py
wisent/core/hyperparameter_optimizer.py
wisent/core/layer.py
wisent/core/lm_eval_harness_ground_truth.py
wisent/core/main.py
wisent/core/managed_cached_benchmarks.py
wisent/core/mixed_benchmark_sampler.py
wisent/core/model_persistence.py
wisent/core/multi_steering.py
wisent/core/parser.py
wisent/core/representation.py
wisent/core/save_results.py
wisent/core/steering.py
wisent/core/steering_method.py
wisent/core/steering_optimizer.py
wisent/core/task_interface.py
wisent/core/task_selector.py
wisent/core/time_estimator.py
wisent/core/timing_calibration.py
wisent/core/universal_subspace.py
wisent/core/user_model_config.py
wisent/core/wisent.py
wisent/core/activations/__init__.py
wisent/core/activations/activation_cache.py
wisent/core/activations/activations.py
wisent/core/activations/activations_collector.py
wisent/core/activations/classifier_inference_strategy.py
wisent/core/activations/extraction_strategy.py
wisent/core/activations/core/__init__.py
wisent/core/activations/core/atoms.py
wisent/core/adapters/__init__.py
wisent/core/adapters/audio.py
wisent/core/adapters/base.py
wisent/core/adapters/multimodal.py
wisent/core/adapters/robotics.py
wisent/core/adapters/text.py
wisent/core/adapters/video.py
wisent-0.7.1181.dist-info/licenses/LICENSE
wisent-0.7.1181.dist-info/METADATA
wisent-0.7.1181.dist-info/WHEEL
wisent-0.7.1181.dist-info/entry_points.txt
wisent-0.7.1181.dist-info/top_level.txt
wisent-0.7.1181.dist-info/RECORD
