Metadata-Version: 2.4
Name: wisent
Version: 0.7.1181
Summary: Monitor and influence AI Brains
Home-page: https://github.com/wisent-ai/wisent
Author: Lukasz Bartoszcze and the Wisent Team
Author-email: lukasz.bartoszcze@wisent.ai
Keywords: nlp,machine learning,language models,safety,guardrails,lm-evaluation-harness
Classifier: Programming Language :: Python :: 3
Classifier: License :: OSI Approved :: MIT License
Classifier: Operating System :: OS Independent
Classifier: Development Status :: 4 - Beta
Classifier: Intended Audience :: Science/Research
Classifier: Topic :: Scientific/Engineering :: Artificial Intelligence
Requires-Python: >=3.8
License-File: LICENSE
Requires-Dist: torch>=1.9.0
Requires-Dist: transformers>=4.20.0
Requires-Dist: tqdm>=4.50.0
Requires-Dist: scikit-learn>=0.24.0
Requires-Dist: pandas>=1.2.0
Requires-Dist: numpy>=1.21.0
Requires-Dist: datasets>=2.0.0
Requires-Dist: sentence-transformers>=2.0.0
Requires-Dist: faiss-cpu>=1.7.0
Requires-Dist: uncensorbench>=0.2.0
Requires-Dist: pebble>=5.0.0
Requires-Dist: latex2sympy2_extended>=1.0.0
Requires-Dist: sae_lens>=0.1.0
Requires-Dist: trl>=0.7.0
Requires-Dist: peft>=0.7.0
Requires-Dist: pyreft==0.1.0
Provides-Extra: harness
Requires-Dist: lm-eval==0.4.8; extra == "harness"
Provides-Extra: cuda
Requires-Dist: flash-attn>=2.5.0; extra == "cuda"
Provides-Extra: sparsify
Requires-Dist: sparsify>=0.1.0; extra == "sparsify"
Dynamic: author
Dynamic: author-email
Dynamic: classifier
Dynamic: description
Dynamic: description-content-type
Dynamic: home-page
Dynamic: keywords
Dynamic: license-file
Dynamic: provides-extra
Dynamic: requires-dist
Dynamic: requires-python
Dynamic: summary
